allennlp_semparse/__init__.py
allennlp_semparse/version.py
allennlp_semparse/common/__init__.py
allennlp_semparse/common/action_space_walker.py
allennlp_semparse/common/date.py
allennlp_semparse/common/errors.py
allennlp_semparse/common/knowledge_graph.py
allennlp_semparse/common/util.py
allennlp_semparse/common/sql/__init__.py
allennlp_semparse/common/sql/text2sql_utils.py
allennlp_semparse/common/wikitables/__init__.py
allennlp_semparse/common/wikitables/table_question_context.py
allennlp_semparse/common/wikitables/wikitables_evaluator.py
allennlp_semparse/dataset_readers/__init__.py
allennlp_semparse/dataset_readers/atis.py
allennlp_semparse/dataset_readers/grammar_based_text2sql.py
allennlp_semparse/dataset_readers/nlvr.py
allennlp_semparse/dataset_readers/template_text2sql.py
allennlp_semparse/dataset_readers/wikitables.py
allennlp_semparse/domain_languages/__init__.py
allennlp_semparse/domain_languages/domain_language.py
allennlp_semparse/domain_languages/nlvr_language.py
allennlp_semparse/domain_languages/wikitables_language.py
allennlp_semparse/fields/__init__.py
allennlp_semparse/fields/knowledge_graph_field.py
allennlp_semparse/fields/production_rule_field.py
allennlp_semparse/models/__init__.py
allennlp_semparse/models/text2sql_parser.py
allennlp_semparse/models/atis/__init__.py
allennlp_semparse/models/atis/atis_semantic_parser.py
allennlp_semparse/models/nlvr/__init__.py
allennlp_semparse/models/nlvr/nlvr_coverage_semantic_parser.py
allennlp_semparse/models/nlvr/nlvr_direct_semantic_parser.py
allennlp_semparse/models/nlvr/nlvr_semantic_parser.py
allennlp_semparse/models/wikitables/__init__.py
allennlp_semparse/models/wikitables/wikitables_erm_semantic_parser.py
allennlp_semparse/models/wikitables/wikitables_mml_semantic_parser.py
allennlp_semparse/models/wikitables/wikitables_semantic_parser.py
allennlp_semparse/nltk_languages/__init__.py
allennlp_semparse/nltk_languages/contexts/__init__.py
allennlp_semparse-0.0.4.dist-info/LICENSE
allennlp_semparse-0.0.4.dist-info/METADATA
allennlp_semparse-0.0.4.dist-info/WHEEL
allennlp_semparse-0.0.4.dist-info/top_level.txt
allennlp_semparse-0.0.4.dist-info/RECORD
