Metadata-Version: 2.1
Name: allennlp-semparse
Version: 0.0.4
Summary: A framework for building semantic parsers (including neural module networks) with AllenNLP, built by the authors of AllenNLP
Home-page: https://github.com/allenai/allennlp-semparse
Author: Allen Institute for Artificial Intelligence
Author-email: allennlp@allenai.org
License: Apache
Keywords: allennlp NLP deep learning machine reading semantic parsing parsers
Platform: UNKNOWN
Classifier: Intended Audience :: Science/Research
Classifier: Development Status :: 3 - Alpha
Classifier: License :: OSI Approved :: Apache Software License
Classifier: Programming Language :: Python :: 3.6
Classifier: Topic :: Scientific/Engineering :: Artificial Intelligence
Requires-Python: >=3.6.1
License-File: LICENSE
Requires-Dist: spacy (<3.0)
Requires-Dist: parsimonious (>=0.8.0)
Requires-Dist: sqlparse (>=0.2.4)
Requires-Dist: unidecode
Requires-Dist: editdistance
Requires-Dist: nltk
Requires-Dist: flaky
Requires-Dist: allennlp (<3.0,>=2.0)
